borscht/ChainGenerator.py
borscht/TextGenerator.py
borscht/__init__.py
borscht-1.1.1.dist-info/LICENSE
borscht-1.1.1.dist-info/METADATA
borscht-1.1.1.dist-info/WHEEL
borscht-1.1.1.dist-info/top_level.txt
borscht-1.1.1.dist-info/RECORD
