Metadata-Version: 2.1
Name: borscht
Version: 1.1.1
Summary: The Python Module of The japanese sentence generator by markov chain.
Home-page: https://github.com/yu-san-19/Borscht
Author: YuSan19
Author-email: ysoga19@gmail.com
Maintainer: YuSan19
Maintainer-email: ysoga19@gmail.com
License: MIT
Platform: UNKNOWN
Requires-Dist: mecab-python3 (==0.996.2)
